anncsu/pa/__init__.py
anncsu/pa/_version.py
anncsu/pa/basesdk.py
anncsu/pa/httpclient.py
anncsu/pa/jsonpost.py
anncsu/pa/pathparam.py
anncsu/pa/py.typed
anncsu/pa/queryparam.py
anncsu/pa/sdk.py
anncsu/pa/sdkconfiguration.py
anncsu/pa/status.py
anncsu/pa/_hooks/__init__.py
anncsu/pa/_hooks/registration.py
anncsu/pa/_hooks/sdkhooks.py
anncsu/pa/_hooks/types.py
anncsu/pa/errors/__init__.py
anncsu/pa/errors/anncsuerror.py
anncsu/pa/errors/apierror.py
anncsu/pa/errors/elencoaccessigetpathparamop.py
anncsu/pa/errors/elencoaccessigetqueryparamop.py
anncsu/pa/errors/elencoaccessipostop.py
anncsu/pa/errors/elencoaccessiproggetpathparamop.py
anncsu/pa/errors/elencoaccessiproggetqueryparamop.py
anncsu/pa/errors/elencoaccessiprogpostop.py
anncsu/pa/errors/elencoodonimigetpathparamop.py
anncsu/pa/errors/elencoodonimigetqueryparamop.py
anncsu/pa/errors/elencoodonimipostop.py
anncsu/pa/errors/elencoodonimiproggetpathparamop.py
anncsu/pa/errors/elencoodonimiproggetqueryparamop.py
anncsu/pa/errors/elencoodonimiprogpostop.py
anncsu/pa/errors/esisteaccessogetpathparamop.py
anncsu/pa/errors/esisteaccessogetqueryparamop.py
anncsu/pa/errors/esisteaccessopostop.py
anncsu/pa/errors/esisteodonimogetpathparamop.py
anncsu/pa/errors/esisteodonimogetqueryparamop.py
anncsu/pa/errors/esisteodonimopostop.py
anncsu/pa/errors/no_response_error.py
anncsu/pa/errors/prognazaccgetpathparamop.py
anncsu/pa/errors/prognazaccgetqueryparamop.py
anncsu/pa/errors/prognazaccpostop.py
anncsu/pa/errors/prognazareagetpathparamop.py
anncsu/pa/errors/prognazareagetqueryparamop.py
anncsu/pa/errors/prognazareapostop.py
anncsu/pa/errors/responsevalidationerror.py
anncsu/pa/errors/show_statusop.py
anncsu/pa/models/__init__.py
anncsu/pa/models/elencoaccessigetpathparamop.py
anncsu/pa/models/elencoaccessigetqueryparamop.py
anncsu/pa/models/elencoaccessipostop.py
anncsu/pa/models/elencoaccessiproggetpathparamop.py
anncsu/pa/models/elencoaccessiproggetqueryparamop.py
anncsu/pa/models/elencoaccessiprogpostop.py
anncsu_sdk-0.0.5.dist-info/METADATA
anncsu_sdk-0.0.5.dist-info/WHEEL
anncsu_sdk-0.0.5.dist-info/licenses/LICENSE
anncsu_sdk-0.0.5.dist-info/RECORD
