Metadata-Version: 2.4
Name: anncsu-sdk
Version: 0.0.5
Summary: ANNCSU Software Development Kit for API consumption
Author-email: Francesco Bartoli <francesco.bartoli@geobeyond.it>
License-File: LICENSE
Requires-Python: >=3.12
Requires-Dist: httpcore>=1.0.9
Requires-Dist: httpx>=0.28.1
Requires-Dist: pydantic>=2.11.2
